pyhesaff/__init__.py
pyhesaff/__main__.py
pyhesaff/_demodata.py
pyhesaff/_pyhesaff.py
pyhesaff/ctypes_interface.py
pyhesaff/libhesaff.so
pyhesaff.libs/libQt5Core-832803ac.so.5.15.3
pyhesaff.libs/libQt5Gui-30d34e12.so.5.15.3
pyhesaff.libs/libQt5OpenGL-a911bbab.so.5.15.3
pyhesaff.libs/libQt5Test-1cb35c93.so.5.15.3
pyhesaff.libs/libQt5Widgets-2e92b9ef.so.5.15.3
pyhesaff.libs/libasound-0ceed182.so.2.0.0
pyhesaff.libs/libblkid-a9167753.so.1.1.0
pyhesaff.libs/libbz2-a1e77c99.so.1.0.6
pyhesaff.libs/libcap-16fca4d2.so.2.48
pyhesaff.libs/libdatrie-584ecbbd.so.1.3.2
pyhesaff.libs/libdc1394-68c67e1a.so.22.1.9
pyhesaff.libs/libffi-3a37023a.so.6.0.2
pyhesaff.libs/libfontconfig-dcb2ce6c.so.1.12.0
pyhesaff.libs/libfreetype-2f3b32b6.so.6.16.1
pyhesaff.libs/libfribidi-a2ddad26.so.0.4.0
pyhesaff.libs/libgcrypt-a1b5cc4c.so.20.2.5
pyhesaff.libs/libgfortran-8f1e9814.so.5.0.0
pyhesaff.libs/libgif-5ed6ffef.so.7.0.0
pyhesaff.libs/libgmodule-2-6c5d2a3f.0.so.0.5600.4
pyhesaff.libs/libgmp-d944b113.so.10.3.2
pyhesaff.libs/libgnutls-68a48e86.so.30.28.2
pyhesaff.libs/libgomp-870cb1d0.so.1.0.0
pyhesaff.libs/libgpg-error-d4e115d0.so.0.24.2
pyhesaff.libs/libgraphite2-a2b39163.so.3.0.1
pyhesaff.libs/libgstapp-1-e25224cd.0.so.0.1601.0
pyhesaff.libs/libgstaudio-1-38324d25.0.so.0.1601.0
pyhesaff.libs/libgstbase-1-47c58434.0.so.0.1601.0
pyhesaff.libs/libgstpbutils-1-7207e21f.0.so.0.1601.0
pyhesaff.libs/libgstreamer-1-2fca8303.0.so.0.1601.0
pyhesaff.libs/libgstriff-1-4bc36ede.0.so.0.1601.0
pyhesaff.libs/libgsttag-1-3e9b8946.0.so.0.1601.0
pyhesaff.libs/libgstvideo-1-ddcb5742.0.so.0.1601.0
pyhesaff.libs/libharfbuzz-26b3d829.so.0.10705.0
pyhesaff.libs/libhogweed-cd4c53be.so.4.5
pyhesaff.libs/libicudata-05640f77.so.60.3
pyhesaff.libs/libicui18n-4fcc01ea.so.60.3
pyhesaff.libs/libicuuc-14201aad.so.60.3
pyhesaff.libs/libidn2-2f4a5893.so.0.3.6
pyhesaff.libs/libjasper-61dc4fbf.so.4.0.0
pyhesaff.libs/libjbig-2504a0c3.so.2.1
pyhesaff.libs/libjpeg-e87d2658.so.62.2.0
pyhesaff-2.1.3.dist-info/METADATA
pyhesaff-2.1.3.dist-info/WHEEL
pyhesaff-2.1.3.dist-info/top_level.txt
pyhesaff-2.1.3.dist-info/RECORD
