Metadata-Version: 2.4
Name: pyhesaff
Version: 2.1.3
Summary: Routines for computation of hessian affine keypoints in images.
Home-page: https://github.com/Erotemic/pyhesaff
Author: Krystian Mikolajczyk, Michal Perdoch, Jon Crall, Avi Weinstock
Author-email: erotemic@gmail.com
License: Apache 2
Classifier: Development Status :: 4 - Beta
Classifier: Intended Audience :: Developers
Classifier: Topic :: Software Development :: Libraries :: Python Modules
Classifier: Topic :: Utilities
Classifier: Programming Language :: Python :: 3.9
Classifier: Programming Language :: Python :: 3.10
Classifier: Programming Language :: Python :: 3.11
Classifier: Programming Language :: Python :: 3.12
Classifier: Programming Language :: Python :: 3.13
Classifier: Programming Language :: Python :: 3.14
Requires-Python: >=3.9
Requires-Dist: numpy>=2.1.0; python_version < "4.0" and python_version >= "3.13"
Requires-Dist: numpy>=1.26.0; python_version < "3.13" and python_version >= "3.12"
Requires-Dist: numpy>=1.23.2; python_version < "3.12" and python_version >= "3.11"
Requires-Dist: numpy>=1.21.6; python_version < "3.11" and python_version >= "3.10"
Requires-Dist: numpy>=1.19.3; python_version < "3.10" and python_version >= "3.9"
Requires-Dist: numpy>=1.19.3; python_version < "3.9" and python_version >= "3.8"
Requires-Dist: ubelt>=1.3.4
Provides-Extra: all
Requires-Dist: numpy>=2.1.0; (python_version < "4.0" and python_version >= "3.13") and extra == "all"
Requires-Dist: numpy>=1.26.0; (python_version < "3.13" and python_version >= "3.12") and extra == "all"
Requires-Dist: numpy>=1.23.2; (python_version < "3.12" and python_version >= "3.11") and extra == "all"
Requires-Dist: numpy>=1.21.6; (python_version < "3.11" and python_version >= "3.10") and extra == "all"
Requires-Dist: numpy>=1.19.3; (python_version < "3.10" and python_version >= "3.9") and extra == "all"
Requires-Dist: numpy>=1.19.3; (python_version < "3.9" and python_version >= "3.8") and extra == "all"
Requires-Dist: ubelt>=1.3.4; extra == "all"
Requires-Dist: utool>=2.2.1; extra == "all"
Requires-Dist: xdoctest>=1.1.5; extra == "all"
Requires-Dist: pytest>=8.1.1; (python_version < "4.0" and python_version >= "3.13") and extra == "all"
Requires-Dist: pytest>=8.1.1; (python_version < "3.13" and python_version >= "3.12") and extra == "all"
Requires-Dist: pytest>=8.1.1; (python_version < "3.12" and python_version >= "3.11") and extra == "all"
Requires-Dist: pytest>=6.2.5; (python_version < "3.11" and python_version >= "3.10") and extra == "all"
Requires-Dist: pytest>=6.2.5; (python_version < "3.10" and python_version >= "3.8") and extra == "all"
Requires-Dist: pytest-cov>=3.0.0; extra == "all"
Requires-Dist: pytest_timeout>=2.3.1; (python_version < "4.0" and python_version >= "3.12") and extra == "all"
Requires-Dist: pytest_timeout>=1.4.2; python_version < "3.12" and extra == "all"
Requires-Dist: coverage>=7.3.0; (python_version < "4.0" and python_version >= "3.12") and extra == "all"
Requires-Dist: coverage>=6.1.1; (python_version < "3.12" and python_version >= "3.10") and extra == "all"
Requires-Dist: coverage>=5.3.1; (python_version < "3.10" and python_version >= "3.9") and extra == "all"
Requires-Dist: coverage>=6.1.1; (python_version < "3.9" and python_version >= "3.8") and extra == "all"
Requires-Dist: coverage>=7.3.0; (python_version < "4.0" and python_version >= "3.12") and extra == "all"
Requires-Dist: coverage>=6.1.1; (python_version < "3.12" and python_version >= "3.10") and extra == "all"
Requires-Dist: coverage>=5.3.1; (python_version < "3.10" and python_version >= "3.9") and extra == "all"
Requires-Dist: coverage>=6.1.1; (python_version < "3.9" and python_version >= "3.8") and extra == "all"
Requires-Dist: requests>=2.27.1; extra == "all"
Requires-Dist: cmake; extra == "all"
Requires-Dist: ninja; extra == "all"
Requires-Dist: scikit-build; extra == "all"
Requires-Dist: setuptools; extra == "all"
Requires-Dist: setuptools_scm[toml]; extra == "all"
Requires-Dist: wheel; extra == "all"
Provides-Extra: headless
Requires-Dist: opencv-python-headless>=4.10.0.84; (python_version < "4.0" and python_version >= "3.13") and extra == "headless"
Requires-Dist: opencv-python-headless>=4.5.5.64; (python_version < "3.13" and python_version >= "3.11") and extra == "headless"
Requires-Dist: opencv-python-headless>=4.5.4.58; (python_version < "3.11" and python_version >= "3.10") and extra == "headless"
Requires-Dist: opencv-python-headless>=3.4.15.55; (python_version < "3.10" and python_version >= "3.9") and extra == "headless"
Provides-Extra: graphics
Requires-Dist: opencv-python>=4.10.0.84; (python_version < "4.0" and python_version >= "3.13") and extra == "graphics"
Requires-Dist: opencv-python>=4.5.5.64; (python_version < "3.13" and python_version >= "3.11") and extra == "graphics"
Requires-Dist: opencv-python>=4.5.4.58; (python_version < "3.11" and python_version >= "3.10") and extra == "graphics"
Requires-Dist: opencv-python>=3.4.15.55; (python_version < "3.10" and python_version >= "3.9") and extra == "graphics"
Provides-Extra: build
Requires-Dist: cmake; extra == "build"
Requires-Dist: ninja; extra == "build"
Requires-Dist: scikit-build; extra == "build"
Requires-Dist: setuptools; extra == "build"
Requires-Dist: setuptools_scm[toml]; extra == "build"
Requires-Dist: wheel; extra == "build"
Provides-Extra: docs
Requires-Dist: sphinx>=5.0.1; extra == "docs"
Requires-Dist: sphinx-autobuild>=2021.3.14; extra == "docs"
Requires-Dist: sphinx_rtd_theme>=1.0.0; extra == "docs"
Requires-Dist: sphinxcontrib-napoleon>=0.7; extra == "docs"
Requires-Dist: sphinx-autoapi>=1.8.4; extra == "docs"
Requires-Dist: Pygments>=2.9.0; extra == "docs"
Requires-Dist: myst_parser>=0.18.0; extra == "docs"
Requires-Dist: sphinx-reredirects>=0.0.1; extra == "docs"
Provides-Extra: optional
Provides-Extra: runtime
Requires-Dist: numpy>=2.1.0; (python_version < "4.0" and python_version >= "3.13") and extra == "runtime"
Requires-Dist: numpy>=1.26.0; (python_version < "3.13" and python_version >= "3.12") and extra == "runtime"
Requires-Dist: numpy>=1.23.2; (python_version < "3.12" and python_version >= "3.11") and extra == "runtime"
Requires-Dist: numpy>=1.21.6; (python_version < "3.11" and python_version >= "3.10") and extra == "runtime"
Requires-Dist: numpy>=1.19.3; (python_version < "3.10" and python_version >= "3.9") and extra == "runtime"
Requires-Dist: numpy>=1.19.3; (python_version < "3.9" and python_version >= "3.8") and extra == "runtime"
Requires-Dist: ubelt>=1.3.4; extra == "runtime"
Provides-Extra: tests
Requires-Dist: utool>=2.2.1; extra == "tests"
Requires-Dist: xdoctest>=1.1.5; extra == "tests"
Requires-Dist: pytest>=8.1.1; (python_version < "4.0" and python_version >= "3.13") and extra == "tests"
Requires-Dist: pytest>=8.1.1; (python_version < "3.13" and python_version >= "3.12") and extra == "tests"
Requires-Dist: pytest>=8.1.1; (python_version < "3.12" and python_version >= "3.11") and extra == "tests"
Requires-Dist: pytest>=6.2.5; (python_version < "3.11" and python_version >= "3.10") and extra == "tests"
Requires-Dist: pytest>=6.2.5; (python_version < "3.10" and python_version >= "3.8") and extra == "tests"
Requires-Dist: pytest-cov>=3.0.0; extra == "tests"
Requires-Dist: pytest_timeout>=2.3.1; (python_version < "4.0" and python_version >= "3.12") and extra == "tests"
Requires-Dist: pytest_timeout>=1.4.2; python_version < "3.12" and extra == "tests"
Requires-Dist: coverage>=7.3.0; (python_version < "4.0" and python_version >= "3.12") and extra == "tests"
Requires-Dist: coverage>=6.1.1; (python_version < "3.12" and python_version >= "3.10") and extra == "tests"
Requires-Dist: coverage>=5.3.1; (python_version < "3.10" and python_version >= "3.9") and extra == "tests"
Requires-Dist: coverage>=6.1.1; (python_version < "3.9" and python_version >= "3.8") and extra == "tests"
Requires-Dist: coverage>=7.3.0; (python_version < "4.0" and python_version >= "3.12") and extra == "tests"
Requires-Dist: coverage>=6.1.1; (python_version < "3.12" and python_version >= "3.10") and extra == "tests"
Requires-Dist: coverage>=5.3.1; (python_version < "3.10" and python_version >= "3.9") and extra == "tests"
Requires-Dist: coverage>=6.1.1; (python_version < "3.9" and python_version >= "3.8") and extra == "tests"
Requires-Dist: requests>=2.27.1; extra == "tests"
Provides-Extra: all-strict
Requires-Dist: numpy==2.1.0; (python_version < "4.0" and python_version >= "3.13") and extra == "all-strict"
Requires-Dist: numpy==1.26.0; (python_version < "3.13" and python_version >= "3.12") and extra == "all-strict"
Requires-Dist: numpy==1.23.2; (python_version < "3.12" and python_version >= "3.11") and extra == "all-strict"
Requires-Dist: numpy==1.21.6; (python_version < "3.11" and python_version >= "3.10") and extra == "all-strict"
Requires-Dist: numpy==1.19.3; (python_version < "3.10" and python_version >= "3.9") and extra == "all-strict"
Requires-Dist: numpy==1.19.3; (python_version < "3.9" and python_version >= "3.8") and extra == "all-strict"
Requires-Dist: ubelt==1.3.4; extra == "all-strict"
Requires-Dist: utool==2.2.1; extra == "all-strict"
Requires-Dist: xdoctest==1.1.5; extra == "all-strict"
Requires-Dist: pytest==8.1.1; (python_version < "4.0" and python_version >= "3.13") and extra == "all-strict"
Requires-Dist: pytest==8.1.1; (python_version < "3.13" and python_version >= "3.12") and extra == "all-strict"
Requires-Dist: pytest==8.1.1; (python_version < "3.12" and python_version >= "3.11") and extra == "all-strict"
Requires-Dist: pytest==6.2.5; (python_version < "3.11" and python_version >= "3.10") and extra == "all-strict"
Requires-Dist: pytest==6.2.5; (python_version < "3.10" and python_version >= "3.8") and extra == "all-strict"
Requires-Dist: pytest-cov==3.0.0; extra == "all-strict"
Requires-Dist: pytest_timeout==2.3.1; (python_version < "4.0" and python_version >= "3.12") and extra == "all-strict"
Requires-Dist: pytest_timeout==1.4.2; python_version < "3.12" and extra == "all-strict"
Requires-Dist: coverage==7.3.0; (python_version < "4.0" and python_version >= "3.12") and extra == "all-strict"
Requires-Dist: coverage==6.1.1; (python_version < "3.12" and python_version >= "3.10") and extra == "all-strict"
Requires-Dist: coverage==5.3.1; (python_version < "3.10" and python_version >= "3.9") and extra == "all-strict"
Requires-Dist: coverage==6.1.1; (python_version < "3.9" and python_version >= "3.8") and extra == "all-strict"
Requires-Dist: coverage==7.3.0; (python_version < "4.0" and python_version >= "3.12") and extra == "all-strict"
Requires-Dist: coverage==6.1.1; (python_version < "3.12" and python_version >= "3.10") and extra == "all-strict"
Requires-Dist: coverage==5.3.1; (python_version < "3.10" and python_version >= "3.9") and extra == "all-strict"
Requires-Dist: coverage==6.1.1; (python_version < "3.9" and python_version >= "3.8") and extra == "all-strict"
Requires-Dist: requests==2.27.1; extra == "all-strict"
Requires-Dist: cmake; extra == "all-strict"
Requires-Dist: ninja; extra == "all-strict"
Requires-Dist: scikit-build; extra == "all-strict"
Requires-Dist: setuptools; extra == "all-strict"
Requires-Dist: setuptools_scm[toml]; extra == "all-strict"
Requires-Dist: wheel; extra == "all-strict"
Provides-Extra: headless-strict
Requires-Dist: opencv-python-headless==4.10.0.84; (python_version < "4.0" and python_version >= "3.13") and extra == "headless-strict"
Requires-Dist: opencv-python-headless==4.5.5.64; (python_version < "3.13" and python_version >= "3.11") and extra == "headless-strict"
Requires-Dist: opencv-python-headless==4.5.4.58; (python_version < "3.11" and python_version >= "3.10") and extra == "headless-strict"
Requires-Dist: opencv-python-headless==3.4.15.55; (python_version < "3.10" and python_version >= "3.9") and extra == "headless-strict"
Provides-Extra: build-strict
Requires-Dist: cmake; extra == "build-strict"
Requires-Dist: ninja; extra == "build-strict"
Requires-Dist: scikit-build; extra == "build-strict"
Requires-Dist: setuptools; extra == "build-strict"
Requires-Dist: setuptools_scm[toml]; extra == "build-strict"
Requires-Dist: wheel; extra == "build-strict"
Provides-Extra: docs-strict
Requires-Dist: sphinx==5.0.1; extra == "docs-strict"
Requires-Dist: sphinx-autobuild==2021.3.14; extra == "docs-strict"
Requires-Dist: sphinx_rtd_theme==1.0.0; extra == "docs-strict"
Requires-Dist: sphinxcontrib-napoleon==0.7; extra == "docs-strict"
Requires-Dist: sphinx-autoapi==1.8.4; extra == "docs-strict"
Requires-Dist: Pygments==2.9.0; extra == "docs-strict"
Requires-Dist: myst_parser==0.18.0; extra == "docs-strict"
Requires-Dist: sphinx-reredirects==0.0.1; extra == "docs-strict"
Provides-Extra: graphics-strict
Requires-Dist: opencv-python==4.10.0.84; (python_version < "4.0" and python_version >= "3.13") and extra == "graphics-strict"
Requires-Dist: opencv-python==4.5.5.64; (python_version < "3.13" and python_version >= "3.11") and extra == "graphics-strict"
Requires-Dist: opencv-python==4.5.4.58; (python_version < "3.11" and python_version >= "3.10") and extra == "graphics-strict"
Requires-Dist: opencv-python==3.4.15.55; (python_version < "3.10" and python_version >= "3.9") and extra == "graphics-strict"
Provides-Extra: optional-strict
Provides-Extra: runtime-strict
Requires-Dist: numpy==2.1.0; (python_version < "4.0" and python_version >= "3.13") and extra == "runtime-strict"
Requires-Dist: numpy==1.26.0; (python_version < "3.13" and python_version >= "3.12") and extra == "runtime-strict"
Requires-Dist: numpy==1.23.2; (python_version < "3.12" and python_version >= "3.11") and extra == "runtime-strict"
Requires-Dist: numpy==1.21.6; (python_version < "3.11" and python_version >= "3.10") and extra == "runtime-strict"
Requires-Dist: numpy==1.19.3; (python_version < "3.10" and python_version >= "3.9") and extra == "runtime-strict"
Requires-Dist: numpy==1.19.3; (python_version < "3.9" and python_version >= "3.8") and extra == "runtime-strict"
Requires-Dist: ubelt==1.3.4; extra == "runtime-strict"
Provides-Extra: tests-strict
Requires-Dist: utool==2.2.1; extra == "tests-strict"
Requires-Dist: xdoctest==1.1.5; extra == "tests-strict"
Requires-Dist: pytest==8.1.1; (python_version < "4.0" and python_version >= "3.13") and extra == "tests-strict"
Requires-Dist: pytest==8.1.1; (python_version < "3.13" and python_version >= "3.12") and extra == "tests-strict"
Requires-Dist: pytest==8.1.1; (python_version < "3.12" and python_version >= "3.11") and extra == "tests-strict"
Requires-Dist: pytest==6.2.5; (python_version < "3.11" and python_version >= "3.10") and extra == "tests-strict"
Requires-Dist: pytest==6.2.5; (python_version < "3.10" and python_version >= "3.8") and extra == "tests-strict"
Requires-Dist: pytest-cov==3.0.0; extra == "tests-strict"
Requires-Dist: pytest_timeout==2.3.1; (python_version < "4.0" and python_version >= "3.12") and extra == "tests-strict"
Requires-Dist: pytest_timeout==1.4.2; python_version < "3.12" and extra == "tests-strict"
Requires-Dist: coverage==7.3.0; (python_version < "4.0" and python_version >= "3.12") and extra == "tests-strict"
Requires-Dist: coverage==6.1.1; (python_version < "3.12" and python_version >= "3.10") and extra == "tests-strict"
Requires-Dist: coverage==5.3.1; (python_version < "3.10" and python_version >= "3.9") and extra == "tests-strict"
Requires-Dist: coverage==6.1.1; (python_version < "3.9" and python_version >= "3.8") and extra == "tests-strict"
Requires-Dist: coverage==7.3.0; (python_version < "4.0" and python_version >= "3.12") and extra == "tests-strict"
Requires-Dist: coverage==6.1.1; (python_version < "3.12" and python_version >= "3.10") and extra == "tests-strict"
Requires-Dist: coverage==5.3.1; (python_version < "3.10" and python_version >= "3.9") and extra == "tests-strict"
Requires-Dist: coverage==6.1.1; (python_version < "3.9" and python_version >= "3.8") and extra == "tests-strict"
Requires-Dist: requests==2.27.1; extra == "tests-strict"
Dynamic: author
Dynamic: author-email
Dynamic: classifier
Dynamic: description
Dynamic: description-content-type
Dynamic: home-page
Dynamic: license
Dynamic: provides-extra
Dynamic: requires-dist
Dynamic: requires-python
Dynamic: summary
